starburst_data_products_client/__init__.py
starburst_data_products_client/galaxy/__init__.py
starburst_data_products_client/galaxy/api/Api.py
starburst_data_products_client/galaxy/api/__init__.py
starburst_data_products_client/galaxy/models/Catalog.py
starburst_data_products_client/galaxy/models/Cluster.py
starburst_data_products_client/galaxy/models/ClusterSearchResult.py
starburst_data_products_client/galaxy/models/Contact.py
starburst_data_products_client/galaxy/models/CreateDataProductRequest.py
starburst_data_products_client/galaxy/models/CreateDataProductResponse.py
starburst_data_products_client/galaxy/models/DataProduct.py
starburst_data_products_client/galaxy/models/Link.py
starburst_data_products_client/galaxy/models/Role.py
starburst_data_products_client/galaxy/models/SchemaMetadata.py
starburst_data_products_client/galaxy/models/Tag.py
starburst_data_products_client/galaxy/models/TagResponse.py
starburst_data_products_client/galaxy/models/User.py
starburst_data_products_client/galaxy/models/__init__.py
starburst_data_products_client/sep/__init__.py
starburst_data_products_client/sep/api/Api.py
starburst_data_products_client/sep/api/__init__.py
starburst_data_products_client/sep/data/AccessMetadata.py
starburst_data_products_client/sep/data/Column.py
starburst_data_products_client/sep/data/DataProduct.py
starburst_data_products_client/sep/data/DataProductSearchResult.py
starburst_data_products_client/sep/data/DataProductWorkflowStatus.py
starburst_data_products_client/sep/data/Domain.py
starburst_data_products_client/sep/data/MaterializedView.py
starburst_data_products_client/sep/data/MaterializedViewImportMetadata.py
starburst_data_products_client/sep/data/MaterializedViewProperties.py
starburst_data_products_client/sep/data/MaterializedViewRefreshMetadata.py
starburst_data_products_client/sep/data/Owner.py
starburst_data_products_client/sep/data/RelevantLinks.py
starburst_data_products_client/sep/data/SampleQuery.py
starburst_data_products_client-0.2.2.dist-info/METADATA
starburst_data_products_client-0.2.2.dist-info/WHEEL
starburst_data_products_client-0.2.2.dist-info/RECORD
