Metadata-Version: 2.4
Name: starburst-data-products-client
Version: 0.2.2
Summary: Client for the Starburst Galaxy and Enterprise data products REST APIs
Author: Starburst Data
Author-email:  <info@starburstdata.com>
Requires-Python: >=3.11,<4.0
Classifier: Programming Language :: Python :: 3
Classifier: Programming Language :: Python :: 3.11
Classifier: Programming Language :: Python :: 3.12
Classifier: Programming Language :: Python :: 3.13
Classifier: Programming Language :: Python :: 3.14
Requires-Dist: marshmallow-dataclass (>=8.7.1,<9.0.0)
Requires-Dist: pytest (>=8.3.5,<9.0.0)
Requires-Dist: requests (>=2.32.3,<3.0.0)
